.coveragerc
Dockerfile
LICENSE
MANIFEST.in
README.rst
dev_requirements.txt
requirements.txt
setup.cfg
setup.py
tox.ini
./__init__.py
./cms.xml
./fabfile.py
./forms.py
./invoice.py
./party.py
./product.py
./product.xml
./sale.py
./shipment.py
./static_file.py
./tree.py
./tree.xml
./tryton.cfg
./webshop.py
./webshop.xml
./locale/ca_ES.po
./locale/de_DE.po
./locale/es_ES.po
./static/css/bootstrap-theme.css
./static/css/bootstrap-theme.css.map
./static/css/bootstrap-theme.min.css
./static/css/bootstrap.css
./static/css/bootstrap.css.map
./static/css/bootstrap.min.css
./static/css/font-awesome.min.css
./static/css/jquery.bxslider.css
./static/css/jquery.pnotify.default.css
./static/css/lightbox.css
./static/css/owl.carousel.css
./static/css/style.css
./static/css/typeaheadjs.css
./static/fonts/FontAwesome.otf
./static/fonts/fontawesome-webfont.eot
./static/fonts/fontawesome-webfont.svg
./static/fonts/fontawesome-webfont.ttf
./static/fonts/fontawesome-webfont.woff
./static/images/button-active.png
./static/images/button-normal.png
./static/images/cart-logo.png
./static/images/close.png
./static/images/controls.png
./static/images/favicon.ico
./static/images/flags.png
./static/images/gnacode-logo.png
./static/images/google-plus-icon.png
./static/images/grabbing.png
./static/images/loading.gif
./static/images/nereid_cart_logo.png
./static/images/next.png
./static/images/no-image.jpg
./static/images/no-product-image.png
./static/images/ok.png
./static/images/prev.png
./static/images/recaptcha-example.gif
./static/images/social.png
./static/images/sold-out.png
./static/images/youtube-meluncurkan-flat-icon-1.jpg
./static/images/youtube-meluncurkan-flat-icon-1.png
./static/images/assurance/customer-service.png
./static/images/assurance/dropicon.psd
./static/images/assurance/heart.png
./static/images/assurance/lock.png
./static/images/assurance/warranty-services.png
./static/images/backgrounds/menbg.png
./static/images/backgrounds/womenbg.png
openlabs_nereid_webshop.egg-info/PKG-INFO
openlabs_nereid_webshop.egg-info/SOURCES.txt
openlabs_nereid_webshop.egg-info/dependency_links.txt
openlabs_nereid_webshop.egg-info/entry_points.txt
openlabs_nereid_webshop.egg-info/not-zip-safe
openlabs_nereid_webshop.egg-info/requires.txt
openlabs_nereid_webshop.egg-info/top_level.txt
